streamdiffusion/__init__.py
streamdiffusion/image_filter.py
streamdiffusion/image_utils.py
streamdiffusion/pip_utils.py
streamdiffusion/pipeline.py
streamdiffusion/acceleration/__init__.py
streamdiffusion/acceleration/sfast/__init__.py
streamdiffusion/acceleration/tensorrt/__init__.py
streamdiffusion/acceleration/tensorrt/builder.py
streamdiffusion/acceleration/tensorrt/engine.py
streamdiffusion/acceleration/tensorrt/models.py
streamdiffusion/acceleration/tensorrt/utilities.py
streamdiffusion/tools/__init__.py
streamdiffusion/tools/install-tensorrt.py
streamdiffusion-0.1.1.dist-info/LICENSE
streamdiffusion-0.1.1.dist-info/METADATA
streamdiffusion-0.1.1.dist-info/WHEEL
streamdiffusion-0.1.1.dist-info/top_level.txt
streamdiffusion-0.1.1.dist-info/RECORD
