Metadata-Version: 2.1
Name: streamdiffusion
Version: 0.1.1
Summary: real-time interactive image generation pipeline
Home-page: https://github.com/cumulo-autumn/StreamDiffusion
Author: Aki, kizamimi, ddPn08, Verb, ramune, teftef6220, Tonimono, Chenfeng Xu, Ararat with the help of all our contributors (https://github.com/cumulo-autumn/StreamDiffusion/graphs/contributors)
Author-email: cumulokyoukai@gmail.com
License: Apache 2.0 License
Keywords: deep learning diffusion pytorch stable diffusion audioldm streamdiffusion real-time
Requires-Python: >=3.10.0
License-File: LICENSE
Requires-Dist: fire
Requires-Dist: omegaconf
Requires-Dist: diffusers ==0.24.0
Requires-Dist: transformers
Requires-Dist: accelerate
Provides-Extra: dev
Requires-Dist: xformers ; extra == 'dev'
Requires-Dist: torch ; extra == 'dev'
Requires-Dist: accelerate ; extra == 'dev'
Requires-Dist: protobuf ==3.20.2 ; extra == 'dev'
Requires-Dist: cuda-python ; extra == 'dev'
Requires-Dist: onnx ==1.15.0 ; extra == 'dev'
Requires-Dist: onnxruntime ==1.16.3 ; extra == 'dev'
Requires-Dist: colored ; extra == 'dev'
Provides-Extra: tensorrt
Requires-Dist: protobuf ==3.20.2 ; extra == 'tensorrt'
Requires-Dist: cuda-python ; extra == 'tensorrt'
Requires-Dist: onnx ==1.15.0 ; extra == 'tensorrt'
Requires-Dist: onnxruntime ==1.16.3 ; extra == 'tensorrt'
Requires-Dist: colored ; extra == 'tensorrt'
Provides-Extra: torch
Requires-Dist: torch ; extra == 'torch'
Requires-Dist: accelerate ; extra == 'torch'
Provides-Extra: xformers
Requires-Dist: xformers ; extra == 'xformers'
